{
 "states": [
{"time":1,"state":{"roads":[],"vehicles":[],"junctions":[]}},
{"time":2,"state":{"roads":[],"vehicles":[],"junctions":[]}},
{"time":3,"state":{"roads":[],"vehicles":[],"junctions":[]}},
{"time":4,"state":{"roads":[],"vehicles":[],"junctions":[]}},
{"time":5,"state":{"roads":[],"vehicles":[],"junctions":[]}},
{"time":6,"state":{"roads":[],"vehicles":[],"junctions":[]}},
{"time":7,"state":{"roads":[],"vehicles":[],"junctions":[]}},
{"time":8,"state":{"roads":[],"vehicles":[],"junctions":[]}},
{"time":9,"state":{"roads":[],"vehicles":[],"junctions":[]}},
{"time":10,"state":{"roads":[],"vehicles":[],"junctions":[]}},
{"time":11,"state":{"roads":[],"vehicles":[],"junctions":[]}},
{"time":12,"state":{"roads":[],"vehicles":[],"junctions":[]}},
{"time":13,"state":{"roads":[],"vehicles":[],"junctions":[]}},
{"time":14,"state":{"roads":[],"vehicles":[],"junctions":[]}},
{"time":15,"state":{"roads":[],"vehicles":[],"junctions":[]}},
{"time":16,"state":{"roads":[],"vehicles":[],"junctions":[]}},
{"time":17,"state":{"roads":[],"vehicles":[],"junctions":[]}},
{"time":18,"state":{"roads":[],"vehicles":[],"junctions":[]}},
{"time":19,"state":{"roads":[],"vehicles":[],"junctions":[]}},
{"time":20,"state":{"roads":[],"vehicles":[],"junctions":[]}},
{"time":21,"state":{"roads":[],"vehicles":[],"junctions":[]}},
{"time":22,"state":{"roads":[],"vehicles":[],"junctions":[]}},
{"time":23,"state":{"roads":[],"vehicles":[],"junctions":[]}},
{"time":24,"state":{"roads":[],"vehicles":[],"junctions":[]}},
{"time":25,"state":{"roads":[],"vehicles":[],"junctions":[]}},
{"time":26,"state":{"roads":[],"vehicles":[],"junctions":[]}},
{"time":27,"state":{"roads":[],"vehicles":[],"junctions":[]}},
{"time":28,"state":{"roads":[],"vehicles":[],"junctions":[]}},
{"time":29,"state":{"roads":[],"vehicles":[],"junctions":[]}},
{"time":30,"state":{"roads":[],"vehicles":[],"junctions":[]}},
{"time":31,"state":{"roads":[],"vehicles":[],"junctions":[]}},
{"time":32,"state":{"roads":[],"vehicles":[],"junctions":[]}},
{"time":33,"state":{"roads":[],"vehicles":[],"junctions":[]}},
{"time":34,"state":{"roads":[],"vehicles":[],"junctions":[]}},
{"time":35,"state":{"roads":[],"vehicles":[],"junctions":[]}},
{"time":36,"state":{"roads":[],"vehicles":[],"junctions":[]}},
{"time":37,"state":{"roads":[],"vehicles":[],"junctions":[]}},
{"time":38,"state":{"roads":[],"vehicles":[],"junctions":[]}},
{"time":39,"state":{"roads":[],"vehicles":[],"junctions":[]}},
{"time":40,"state":{"roads":[],"vehicles":[],"junctions":[]}},
{"time":41,"state":{"roads":[],"vehicles":[],"junctions":[]}},
{"time":42,"state":{"roads":[],"vehicles":[],"junctions":[]}},
{"time":43,"state":{"roads":[],"vehicles":[],"junctions":[]}},
{"time":44,"state":{"roads":[],"vehicles":[],"junctions":[]}},
{"time":45,"state":{"roads":[],"vehicles":[],"junctions":[]}},
{"time":46,"state":{"roads":[],"vehicles":[],"junctions":[]}},
{"time":47,"state":{"roads":[],"vehicles":[],"junctions":[]}},
{"time":48,"state":{"roads":[],"vehicles":[],"junctions":[]}},
{"time":49,"state":{"roads":[],"vehicles":[],"junctions":[]}},
{"time":50,"state":{"roads":[],"vehicles":[],"junctions":[]}},
{"time":51,"state":{"roads":[],"vehicles":[],"junctions":[]}},
{"time":52,"state":{"roads":[],"vehicles":[],"junctions":[]}},
{"time":53,"state":{"roads":[],"vehicles":[],"junctions":[]}},
{"time":54,"state":{"roads":[],"vehicles":[],"junctions":[]}},
{"time":55,"state":{"roads":[],"vehicles":[],"junctions":[]}},
{"time":56,"state":{"roads":[],"vehicles":[],"junctions":[]}},
{"time":57,"state":{"roads":[],"vehicles":[],"junctions":[]}},
{"time":58,"state":{"roads":[],"vehicles":[],"junctions":[]}},
{"time":59,"state":{"roads":[],"vehicles":[],"junctions":[]}},
{"time":60,"state":{"roads":[],"vehicles":[],"junctions":[]}},
{"time":61,"state":{"roads":[],"vehicles":[],"junctions":[]}},
{"time":62,"state":{"roads":[],"vehicles":[],"junctions":[]}},
{"time":63,"state":{"roads":[],"vehicles":[],"junctions":[]}},
{"time":64,"state":{"roads":[],"vehicles":[],"junctions":[]}},
{"time":65,"state":{"roads":[],"vehicles":[],"junctions":[]}},
{"time":66,"state":{"roads":[],"vehicles":[],"junctions":[]}},
{"time":67,"state":{"roads":[],"vehicles":[],"junctions":[]}},
{"time":68,"state":{"roads":[],"vehicles":[],"junctions":[]}},
{"time":69,"state":{"roads":[],"vehicles":[],"junctions":[]}},
{"time":70,"state":{"roads":[],"vehicles":[],"junctions":[]}},
{"time":71,"state":{"roads":[],"vehicles":[],"junctions":[]}},
{"time":72,"state":{"roads":[],"vehicles":[],"junctions":[]}},
{"time":73,"state":{"roads":[],"vehicles":[],"junctions":[]}},
{"time":74,"state":{"roads":[],"vehicles":[],"junctions":[]}},
{"time":75,"state":{"roads":[],"vehicles":[],"junctions":[]}},
{"time":76,"state":{"roads":[],"vehicles":[],"junctions":[]}},
{"time":77,"state":{"roads":[],"vehicles":[],"junctions":[]}},
{"time":78,"state":{"roads":[],"vehicles":[],"junctions":[]}},
{"time":79,"state":{"roads":[],"vehicles":[],"junctions":[]}},
{"time":80,"state":{"roads":[],"vehicles":[],"junctions":[]}},
{"time":81,"state":{"roads":[],"vehicles":[],"junctions":[]}},
{"time":82,"state":{"roads":[],"vehicles":[],"junctions":[]}},
{"time":83,"state":{"roads":[],"vehicles":[],"junctions":[]}},
{"time":84,"state":{"roads":[],"vehicles":[],"junctions":[]}},
{"time":85,"state":{"roads":[],"vehicles":[],"junctions":[]}},
{"time":86,"state":{"roads":[],"vehicles":[],"junctions":[]}},
{"time":87,"state":{"roads":[],"vehicles":[],"junctions":[]}},
{"time":88,"state":{"roads":[],"vehicles":[],"junctions":[]}},
{"time":89,"state":{"roads":[],"vehicles":[],"junctions":[]}},
{"time":90,"state":{"roads":[],"vehicles":[],"junctions":[]}},
{"time":91,"state":{"roads":[],"vehicles":[],"junctions":[]}},
{"time":92,"state":{"roads":[],"vehicles":[],"junctions":[]}},
{"time":93,"state":{"roads":[],"vehicles":[],"junctions":[]}},
{"time":94,"state":{"roads":[],"vehicles":[],"junctions":[]}},
{"time":95,"state":{"roads":[],"vehicles":[],"junctions":[]}},
{"time":96,"state":{"roads":[],"vehicles":[],"junctions":[]}},
{"time":97,"state":{"roads":[],"vehicles":[],"junctions":[]}},
{"time":98,"state":{"roads":[],"vehicles":[],"junctions":[]}},
{"time":99,"state":{"roads":[],"vehicles":[],"junctions":[]}},
{"time":100,"state":{"roads":[],"vehicles":[],"junctions":[]}},
{"time":101,"state":{"roads":[],"vehicles":[],"junctions":[]}},
{"time":102,"state":{"roads":[],"vehicles":[],"junctions":[]}},
{"time":103,"state":{"roads":[],"vehicles":[],"junctions":[]}},
{"time":104,"state":{"roads":[],"vehicles":[],"junctions":[]}},
{"time":105,"state":{"roads":[],"vehicles":[],"junctions":[]}},
{"time":106,"state":{"roads":[],"vehicles":[],"junctions":[]}},
{"time":107,"state":{"roads":[],"vehicles":[],"junctions":[]}},
{"time":108,"state":{"roads":[],"vehicles":[],"junctions":[]}},
{"time":109,"state":{"roads":[],"vehicles":[],"junctions":[]}},
{"time":110,"state":{"roads":[],"vehicles":[],"junctions":[]}},
{"time":111,"state":{"roads":[],"vehicles":[],"junctions":[]}},
{"time":112,"state":{"roads":[],"vehicles":[],"junctions":[]}},
{"time":113,"state":{"roads":[],"vehicles":[],"junctions":[]}},
{"time":114,"state":{"roads":[],"vehicles":[],"junctions":[]}},
{"time":115,"state":{"roads":[],"vehicles":[],"junctions":[]}},
{"time":116,"state":{"roads":[],"vehicles":[],"junctions":[]}},
{"time":117,"state":{"roads":[],"vehicles":[],"junctions":[]}},
{"time":118,"state":{"roads":[],"vehicles":[],"junctions":[]}},
{"time":119,"state":{"roads":[],"vehicles":[],"junctions":[]}},
{"time":120,"state":{"roads":[],"vehicles":[],"junctions":[]}},
{"time":121,"state":{"roads":[],"vehicles":[],"junctions":[]}},
{"time":122,"state":{"roads":[],"vehicles":[],"junctions":[]}},
{"time":123,"state":{"roads":[],"vehicles":[],"junctions":[]}},
{"time":124,"state":{"roads":[],"vehicles":[],"junctions":[]}},
{"time":125,"state":{"roads":[],"vehicles":[],"junctions":[]}},
{"time":126,"state":{"roads":[],"vehicles":[],"junctions":[]}},
{"time":127,"state":{"roads":[],"vehicles":[],"junctions":[]}},
{"time":128,"state":{"roads":[],"vehicles":[],"junctions":[]}},
{"time":129,"state":{"roads":[],"vehicles":[],"junctions":[]}},
{"time":130,"state":{"roads":[],"vehicles":[],"junctions":[]}},
{"time":131,"state":{"roads":[],"vehicles":[],"junctions":[]}},
{"time":132,"state":{"roads":[],"vehicles":[],"junctions":[]}},
{"time":133,"state":{"roads":[],"vehicles":[],"junctions":[]}},
{"time":134,"state":{"roads":[],"vehicles":[],"junctions":[]}},
{"time":135,"state":{"roads":[],"vehicles":[],"junctions":[]}},
{"time":136,"state":{"roads":[],"vehicles":[],"junctions":[]}},
{"time":137,"state":{"roads":[],"vehicles":[],"junctions":[]}},
{"time":138,"state":{"roads":[],"vehicles":[],"junctions":[]}},
{"time":139,"state":{"roads":[],"vehicles":[],"junctions":[]}},
{"time":140,"state":{"roads":[],"vehicles":[],"junctions":[]}},
{"time":141,"state":{"roads":[],"vehicles":[],"junctions":[]}},
{"time":142,"state":{"roads":[],"vehicles":[],"junctions":[]}},
{"time":143,"state":{"roads":[],"vehicles":[],"junctions":[]}},
{"time":144,"state":{"roads":[],"vehicles":[],"junctions":[]}},
{"time":145,"state":{"roads":[],"vehicles":[],"junctions":[]}},
{"time":146,"state":{"roads":[],"vehicles":[],"junctions":[]}},
{"time":147,"state":{"roads":[],"vehicles":[],"junctions":[]}},
{"time":148,"state":{"roads":[],"vehicles":[],"junctions":[]}},
{"time":149,"state":{"roads":[],"vehicles":[],"junctions":[]}},
{"time":150,"state":{"roads":[],"vehicles":[],"junctions":[]}}
]
}
